checklist_plus/__init__.py
checklist_plus/abstract_test.py
checklist_plus/config.py
checklist_plus/config.yaml
checklist_plus/expect.py
checklist_plus/multilingual.py
checklist_plus/pred_wrapper.py
checklist_plus/test_suite.py
checklist_plus/test_types.py
checklist_plus/config/text_generation/default_generation.yaml
checklist_plus/data/names.json
checklist_plus/data/wikidata.pkl
checklist_plus/data/lexicons/basic.json
checklist_plus/editor/__init__.py
checklist_plus/editor/base.py
checklist_plus/editor/llm.py
checklist_plus/perturb/__init__.py
checklist_plus/perturb/base.py
checklist_plus/perturb/llm.py
checklist_plus/text_generation/__init__.py
checklist_plus/text_generation/base.py
checklist_plus/text_generation/llm.py
checklist_plus/text_generation/masked_lm.py
checklist_plus/text_generation/models.py
checklist_plus/viewer/__init__.py
checklist_plus/viewer/fake_data.py
checklist_plus/viewer/suite_summarizer.py
checklist_plus/viewer/template_editor.py
checklist_plus/viewer/test_summarizer.py
checklist_plus/viewer/viewer.py
checklist_plus/viewer/static/__init__.py
checklist_plus/viewer/static/bundle.js
checklist_plus/viewer/static/bundle.js.map
checklist_plus/viewer/static/custom.js
checklist_plus/viewer/static/extension.js
checklist_plus/viewer/static/index.js
checklist_plus/viewer/static/index.js.map
checklist_plus-0.2.0.dist-info/licenses/LICENSE
checklist_plus-0.2.0.dist-info/METADATA
checklist_plus-0.2.0.dist-info/WHEEL
checklist_plus-0.2.0.dist-info/entry_points.txt
checklist_plus-0.2.0.dist-info/top_level.txt
checklist_plus-0.2.0.dist-info/RECORD
