Metadata-Version: 2.4
Name: checklist_plus
Version: 0.2.0
Summary: LLM-Enhanced CheckList: AI-Powered Behavioral Testing of NLP Models
Home-page: https://github.com/cowana-ai/checklist-plus
Author: Marco Tulio Ribeiro (Original CheckList)
Author-email: Chingis Owana <your.email@example.com>
License: MIT
Project-URL: Homepage, https://github.com/cowana-ai/checklist_plus
Project-URL: Documentation, https://checklist-plus.readthedocs.io/
Project-URL: Repository, https://github.com/cowana-ai/checklist_plus.git
Project-URL: Bug Tracker, https://github.com/cowana-ai/checklist_plus/issues
Project-URL: Original CheckList, https://github.com/marcotcr/checklist
Keywords: nlp,testing,llm,behavioral-testing,model-evaluation,ai,checklist
Classifier: Development Status :: 4 - Beta
Classifier: Intended Audience :: Developers
Classifier: Intended Audience :: Science/Research
Classifier: License :: OSI Approved :: MIT License
Classifier: Programming Language :: Python :: 3
Classifier: Programming Language :: Python :: 3.9
Classifier: Programming Language :: Python :: 3.10
Classifier: Programming Language :: Python :: 3.11
Classifier: Programming Language :: Python :: 3.12
Classifier: Topic :: Scientific/Engineering :: Artificial Intelligence
Classifier: Topic :: Software Development :: Testing
Requires-Python: >=3.9
License-File: LICENSE
Requires-Dist: numpy>=1.18
Requires-Dist: spacy>=2.2
Requires-Dist: munch>=2.5
Requires-Dist: dill>=0.3.1
Requires-Dist: jupyter>=1.0
Requires-Dist: ipywidgets>=7.5
Requires-Dist: transformers>=2.8
Requires-Dist: patternfork-nosql
Requires-Dist: pycountry
Requires-Dist: openai>=1.0.0
Requires-Dist: anthropic>=0.3.0
Requires-Dist: tiktoken>=0.5.0
Requires-Dist: tenacity>=8.0.0
Requires-Dist: pydantic==1.10.9
Requires-Dist: aiohttp>=3.8.0
Requires-Dist: python-dotenv>=1.0.0
Requires-Dist: jsonschema>=4.0.0
Requires-Dist: langchain[all]>=0.0.27
Requires-Dist: langchain-community>=0.0.38
Requires-Dist: langchain-openai>=0.1.25
Requires-Dist: hydra-core>=1.3.2
Requires-Dist: pip>=25.2
Provides-Extra: huggingface
Requires-Dist: torch>=1.9.0; extra == "huggingface"
Requires-Dist: datasets>=2.0.0; extra == "huggingface"
Requires-Dist: accelerate>=0.20.0; extra == "huggingface"
Requires-Dist: transformers[torch]>=4.21.0; extra == "huggingface"
Provides-Extra: visualization
Requires-Dist: plotly>=5.0.0; extra == "visualization"
Requires-Dist: dash>=2.0.0; extra == "visualization"
Requires-Dist: seaborn>=0.11.0; extra == "visualization"
Requires-Dist: matplotlib>=3.5.0; extra == "visualization"
Provides-Extra: multimodal
Requires-Dist: pillow>=8.0.0; extra == "multimodal"
Requires-Dist: opencv-python>=4.5.0; extra == "multimodal"
Requires-Dist: requests>=2.25.0; extra == "multimodal"
Provides-Extra: dev
Requires-Dist: pytest>=7.0.0; extra == "dev"
Requires-Dist: pre-commit; extra == "dev"
Dynamic: home-page
Dynamic: license-file
Dynamic: requires-python
